ppp_connectors/__init__.py
ppp_connectors/api_connectors/__init__.py
ppp_connectors/api_connectors/broker.py
ppp_connectors/api_connectors/flashpoint.py
ppp_connectors/api_connectors/generic.py
ppp_connectors/api_connectors/ipqs.py
ppp_connectors/api_connectors/spycloud.py
ppp_connectors/api_connectors/twilio.py
ppp_connectors/api_connectors/urlscan.py
ppp_connectors/broker.py
ppp_connectors/dbms_connectors/__init__.py
ppp_connectors/dbms_connectors/elasticsearch.py
ppp_connectors/dbms_connectors/mongo.py
ppp_connectors/dbms_connectors/mongo_async.py
ppp_connectors/dbms_connectors/odbc.py
ppp_connectors/dbms_connectors/splunk.py
ppp_connectors/helpers.py
ppp_connectors/tests/__init__.py
ppp_connectors/tests/conftest.py
ppp_connectors/tests/test_broker/test_integration_broker.py
ppp_connectors/tests/test_broker/test_unit_asyncbroker.py
ppp_connectors/tests/test_broker/test_unit_broker.py
ppp_connectors/tests/test_elasticsearch/test_unit_elasticsearch.py
ppp_connectors/tests/test_flashpoint/cassettes/test_flashpoint_search_fraud_vcr.yaml
ppp_connectors/tests/test_flashpoint/test_integration_flashpoint.py
ppp_connectors/tests/test_flashpoint/test_unit_async_flashpoint.py
ppp_connectors/tests/test_flashpoint/test_unit_flashpoint.py
ppp_connectors/tests/test_generic/cassettes/test_generic_get_github_api.yaml
ppp_connectors/tests/test_generic/test_integration_generic_connector.py
ppp_connectors/tests/test_generic/test_unit_async_generic_connector.py
ppp_connectors/tests/test_generic/test_unit_generic_connector.py
ppp_connectors/tests/test_ipqs/__init__.py
ppp_connectors/tests/test_ipqs/cassettes/test_ipqs_malicious_url_vcr.yaml
ppp_connectors/tests/test_ipqs/test_integration_ipqs.py
ppp_connectors/tests/test_ipqs/test_unit_async_ipqs.py
ppp_connectors/tests/test_ipqs/test_unit_ipqs.py
ppp_connectors/tests/test_mongodb/test_unit_async_mongo.py
ppp_connectors/tests/test_mongodb/test_unit_mongo.py
ppp_connectors/tests/test_odbc/test_unit_odbc.py
ppp_connectors-1.1.13.dist-info/METADATA
ppp_connectors-1.1.13.dist-info/WHEEL
ppp_connectors-1.1.13.dist-info/RECORD
